pirate_ledger/__init__.py
pirate_ledger/commands_handler.py
pirate_ledger/data_handler.py
pirate_ledger/helpers.py
pirate_ledger/main.py
pirate_ledger/cli/__init__.py
pirate_ledger/cli/prompts.py
pirate_ledger/cli/validators.py
pirate_ledger/commands/__init__.py
pirate_ledger/commands/crew.py
pirate_ledger/commands/note.py
pirate_ledger-1.0.1.dist-info/LICENSE
pirate_ledger-1.0.1.dist-info/METADATA
pirate_ledger-1.0.1.dist-info/WHEEL
pirate_ledger-1.0.1.dist-info/entry_points.txt
pirate_ledger-1.0.1.dist-info/top_level.txt
pirate_ledger-1.0.1.dist-info/RECORD
